{"execution_id":"01K7DS160ZH99Q9KJSCJH2GV6D","query_id":5915771,"is_execution_finished":true,"state":"QUERY_STATE_COMPLETED","submitted_at":"2025-10-13T03:15:10.494511Z","expires_at":"2026-01-11T03:16:50.449526Z","execution_started_at":"2025-10-13T03:15:31.93699Z","execution_ended_at":"2025-10-13T03:16:50.449521Z","result":{"rows":[{"balance_bnb":0.00009,"day":"2025-09-29 00:00:00.000 UTC","inflow_bnb":0.0001,"net_bnb":0.00009,"outflow_bnb":0.00001},{"balance_bnb":0.00009,"day":"2025-10-06 00:00:00.000 UTC","inflow_bnb":0.001,"net_bnb":0,"outflow_bnb":0.001}],"metadata":{"column_names":["day","inflow_bnb","outflow_bnb","net_bnb","balance_bnb"],"column_types":["timestamp(3) with time zone","double","double","double","double"],"row_count":2,"result_set_bytes":80,"total_row_count":2,"total_result_set_bytes":80,"datapoint_count":10,"pending_time_millis":21442,"execution_time_millis":78512}}}